[
  {
    "id": "3",
    "nom": "HTML",
    "categorie": "Langages",
    "image": "images/skills/20231229100957.png"
  },
  {
    "id": "4",
    "nom": "CSS",
    "categorie": "Langages",
    "image": "images/skills/20231229101105.png"
  },
  {
    "id": "6",
    "nom": "JavaScript",
    "categorie": "Langages",
    "image": "images/skills/20231229101153.png"
  },
  {
    "id": "7",
    "nom": "PHP",
    "categorie": "Langages",
    "image": "images/skills/20231229104228.png"
  },
  {
    "id": "8",
    "nom": "Laravel",
    "categorie": "Frameworks",
    "image": "images/skills/20231207091841.png"
  },
  {
    "id": "9",
    "nom": "MySQL",
    "categorie": "SGBD",
    "image": "images/skills/20231207091926.png"
  },
  {
    "id": "10",
    "nom": "PostgreSQL",
    "categorie": "SGBD",
    "image": "images/skills/20231207092004.png"
  },
  {
    "id": "11",
    "nom": "NodeJS",
    "categorie": "Frameworks",
    "image": "images/skills/20231207092019.png"
  },
  {
    "id": "12",
    "nom": "Java",
    "categorie": "Langages",
    "image": "images/skills/20231207092028.png"
  },
  {
    "id": "13",
    "nom": "Python",
    "categorie": "Langages",
    "image": "images/skills/20231207092039.png"
  },
  {
    "id": "14",
    "nom": "IntelliJ",
    "categorie": "Outils",
    "image": "images/skills/20231207092107.png"
  },
  {
    "id": "15",
    "nom": "PHPStorm",
    "categorie": "Outils",
    "image": "images/skills/20231207092324.png"
  },
  {
    "id": "16",
    "nom": "PyCharm",
    "categorie": "Outils",
    "image": "images/skills/20231207092405.png"
  },
  {
    "id": "17",
    "nom": "Git",
    "categorie": "Outils",
    "image": "images/skills/20231229101406.png"
  },
  {
    "id": "18",
    "nom": "VsCode",
    "categorie": "Outils",
    "image": "images/skills/20231229101444.png"
  },
  {
    "id": "19",
    "nom": "Debian",
    "categorie": "OS",
    "image": "images/skills/20231207092451.png"
  },
  {
    "id": "20",
    "nom": "Fedora",
    "categorie": "OS",
    "image": "images/skills/20231207092509.png"
  },
  {
    "id": "21",
    "nom": "Windows",
    "categorie": "OS",
    "image": "images/skills/20240818142758.png"
  },
  {
    "id": "22",
    "nom": "Eclipse",
    "categorie": "Outils",
    "image": "images/skills/20240818143048.png"
  },
  {
    "id": "23",
    "nom": "TypeScript",
    "categorie": "Langages",
    "image": "images/skills/20240818143152.png"
  },
  {
    "id": "24",
    "nom": "Angular",
    "categorie": "Frameworks",
    "image": "images/skills/20240818143335.png"
  },
  {
    "id": "25",
    "nom": "React",
    "categorie": "Frameworks",
    "image": "images/skills/20240818143732.png"
  },
  {
    "id": "26",
    "nom": "Vaadin",
    "categorie": "Frameworks",
    "image": "images/skills/20240818143833.png"
  },
  {
    "id": "27",
    "nom": "Selenium",
    "categorie": "Tests",
    "image": "images/skills/20240818144409.png"
  },
  {
    "id": "28",
    "nom": "JUnit 5",
    "categorie": "Tests",
    "image": "images/skills/20240818144516.png"
  },
  {
    "id": "29",
    "nom": "Jubula",
    "categorie": "Tests",
    "image": "images/skills/20240819120641.png"
  },
  {
    "id": "30",
    "nom": "Wildfly",
    "categorie": "Serveur applications",
    "image": "images/skills/20240902150336.png"
  },
  {
    "id": "32",
    "nom": "Spring",
    "categorie": "Frameworks",
    "image": "images/skills/spring-boot.svg"
  },
  {
    "id": "33",
    "nom": "NextJS",
    "categorie": "Frameworks",
    "image": "images/skills/nextjs.svg"
  },
  {
    "id": "34",
    "nom": "React Native",
    "categorie": "Frameworks",
    "image": "images/skills/20240818143732.png"
  },
  {
    "id": "35",
    "nom": "MongoDB",
    "categorie": "SGBD",
    "image": "images/skills/mongodb.svg"
  },
  {
    "id": "36",
    "nom": "Neo4J",
    "categorie": "SGBD",
    "image": "images/skills/neo4j.png"
  },
  {
    "id": "37",
    "nom": "Docker",
    "categorie": "DevOps",
    "image": "images/skills/docker.png"
  },
  {
    "id": "38",
    "nom": "Nomad",
    "categorie": "DevOps",
    "image": "images/skills/nomad.png"
  }
]
